legume_nutrient_dashboard/__init__.py
legume_nutrient_dashboard/analysis.py
legume_nutrient_dashboard/cleaning.py
legume_nutrient_dashboard-0.1.1.dist-info/WHEEL
legume_nutrient_dashboard-0.1.1.dist-info/METADATA
legume_nutrient_dashboard-0.1.1.dist-info/RECORD
