Metadata-Version: 2.3
Name: legume-nutrient-dashboard
Version: 0.1.1
Summary: Interactive dashboard for analyzing legume nutrient data from USDA FoodData Central
Keywords: nutrition,legumes,USDA,dashboard,data-analysis
Author: Your Name
Author-email: Your Name <your.email@example.com>
License: MIT
Classifier: Development Status :: 3 - Alpha
Classifier: Intended Audience :: Science/Research
Classifier: License :: OSI Approved :: MIT License
Classifier: Programming Language :: Python :: 3
Classifier: Programming Language :: Python :: 3.11
Classifier: Programming Language :: Python :: 3.12
Classifier: Topic :: Scientific/Engineering :: Information Analysis
Classifier: Operating System :: OS Independent
Requires-Dist: requests>=2.31.0
Requires-Dist: pandas>=2.3.3
Requires-Dist: numpy>=2.3.5
Requires-Dist: matplotlib>=3.10.6
Requires-Dist: seaborn>=0.13.2
Requires-Dist: plotly>=6.5.0
Requires-Dist: streamlit>=1.40.0
Maintainer: Your Name
Maintainer-email: Your Name <your.email@example.com>
Requires-Python: >=3.11
Project-URL: Documentation, https://Tubbers03.github.io/Individual-Legume-Data/
Project-URL: Homepage, https://github.com/Tubbers03/Individual-Legume-Data
Project-URL: Issues, https://github.com/Tubbers03/Individual-Legume-Data/issues
Project-URL: Repository, https://github.com/Tubbers03/Individual-Legume-Data
